{
  "schemaVersion": 1,
  "id": "delimitedanvils",
  "version": "${version}",
  "name": "DelimitedAnvils",
  "description": "Mineable Bedrock. Duh",
  "authors": [],
  "contact": {},
  "license": "All-Rights-Reserved",
  "environment": "*",
  "entrypoints": {
    "client": [
    ],
    "main": [
      "com.drtdrc.delimitedanvils.DelimitedAnvils"
    ]
  },
  "mixins": [
    "delimitedanvils.mixins.json"
  ],
  "depends": {
    "fabricloader": ">=${loader_version}",
    "fabric": "*",
    "minecraft": "${minecraft_version}"
  }
}
